tdasampling/__init__.py
tdasampling/algorithm.py
tdasampling/walking.py
tdasampling/search_space/__init__.py
tdasampling/search_space/search_space.py
tdasampling-1.0.3.data/scripts/sampling-setup
tdasampling-1.0.3.data/scripts/tdasampling
tdasampling-1.0.3.dist-info/DESCRIPTION.rst
tdasampling-1.0.3.dist-info/METADATA
tdasampling-1.0.3.dist-info/RECORD
tdasampling-1.0.3.dist-info/WHEEL
tdasampling-1.0.3.dist-info/dependency_links.txt
tdasampling-1.0.3.dist-info/metadata.json
tdasampling-1.0.3.dist-info/top_level.txt
