Metadata-Version: 2.0
Name: tdasampling
Version: 1.0.3
Summary: Compute dense samples of real algebraic varieties for use with topological data analysis tools.
Home-page: https://github.com/P-Edwards/tdasampling
Author: Parker Edwards
Author-email: pedwards@ufl.edu
License: MIT
Platform: UNKNOWN
Classifier: Development Status :: 3 - Alpha
Classifier: License :: OSI Approved :: MIT License
Classifier: Programming Language :: Python :: 2.7
Requires-Dist: numpy
Requires-Dist: Rtree
Requires-Dist: sympy
